{
    "name": "CoralGen",
    "description": "When fully submerged in water, you will gain Regeneration III.",
    "condition": {
        "type": "origins:submerged_in",
        "fluid": "minecraft:water"
    },
    "type": "origins:stacking_effect",
    "min_stacks": 0,
    "max_stacks": 1,
    "duration_per_stack": 2,
    "effect": [
        {
            "id": "minecraft:regeneration",
            "amplifier": 2,
            "ambient": true,
            "show_particles": false,
            "show_icon": true
        }
    ]
}
