{
  "portraitScale": 2.1,
  "portraitTranslation": [ -0.75, -0.91, 0 ],
  "profileScale": 0.8,
  "profileTranslation": [ 0, 0.4, 0 ],
  "rootBone": "draliliy",
  "animations": {

  },
  "poses": {
    "standing": {
      "poseTypes": ["STAND", "NONE", "PORTRAIT", "PROFILE"],
      "isBattle": false,
      "animations": [
        "q.look('head')",
        "q.bedrock('dralily', 'ground_idle')"
      ],
      "quirks": ["q.bedrock_quirk('dralily', 'blink')"]
    },
    "walking": {
      "poseTypes": [ "WALK" ],
      "animations": [
        "q.bedrock('dralily', 'ground_walk')"
      ],
      "quirks": ["q.bedrock_quirk('dralily', 'blink')"]
    }
  }
}
